udyndns/__init__.py
udyndns/__main__.py
udyndns/version.py
udyndns-0.0.4.dist-info/LICENSE
udyndns-0.0.4.dist-info/METADATA
udyndns-0.0.4.dist-info/WHEEL
udyndns-0.0.4.dist-info/top_level.txt
udyndns-0.0.4.dist-info/RECORD
